setup.py
distributions_aws_foundation/Binomialdistribution.py
distributions_aws_foundation/Gaussiandistribution.py
distributions_aws_foundation/Generaldistribution.py
distributions_aws_foundation/__init__.py
distributions_aws_foundation.egg-info/PKG-INFO
distributions_aws_foundation.egg-info/SOURCES.txt
distributions_aws_foundation.egg-info/dependency_links.txt
distributions_aws_foundation.egg-info/not-zip-safe
distributions_aws_foundation.egg-info/top_level.txt